LICENSE
MANIFEST.in
setup.cfg
setup.py
versioneer.py
bin/sra_dump
srastream/__init__.py
srastream/_version.py
srastream/utils.py
srastream/writers.py
srastream.egg-info/PKG-INFO
srastream.egg-info/SOURCES.txt
srastream.egg-info/dependency_links.txt
srastream.egg-info/requires.txt
srastream.egg-info/top_level.txt
tests/test_sra.py