Metadata-Version: 1.1
Name: srastream
Version: 0.1.1
Summary: Utilities for streaming NGS reads from SRA accessions.
Home-page: https://github.com/jdidion/srastream
Author: John Didion
Author-email: john.didion@nih.gov
License: Public Domain
Platform: UNKNOWN
Classifier: Development Status :: 3 - Alpha
Classifier: Intended Audience :: Developers
Classifier: Topic :: Software Development :: Libraries :: Python Modules
Classifier: Topic :: Scientific/Engineering :: Bio-Informatics
Classifier: License :: Public Domain
Classifier: Programming Language :: Python :: 3.3
Classifier: Programming Language :: Python :: 3.4
Classifier: Programming Language :: Python :: 3.5
Classifier: Programming Language :: Python :: 3.6
